golos/__init__.py
golos/api.py
golos/base58.py
golos/broadcast.py
golos/exceptions.py
golos/extras.py
golos/key.py
golos/operations.py
golos/storage.py
golos/types.py
golos/ws_client.py
golos_python-1.1.0.data/scripts/golos_call
golos_python-1.1.0.dist-info/LICENSE
golos_python-1.1.0.dist-info/METADATA
golos_python-1.1.0.dist-info/WHEEL
golos_python-1.1.0.dist-info/top_level.txt
golos_python-1.1.0.dist-info/RECORD
