Metadata-Version: 2.1
Name: golos-python
Version: 1.1.0
Summary: Golos Python API by Privex Inc
Home-page: https://github.com/Privex/golos-python
Author: Chris (Someguy123) @ Privex
Author-email: chris@privex.io
License: MIT
Platform: UNKNOWN
Classifier: Programming Language :: Python :: 3
Classifier: Programming Language :: Python :: 3.6
Classifier: Programming Language :: Python :: 3.7
Classifier: Programming Language :: Python :: 3.8
Classifier: License :: OSI Approved :: MIT License
Classifier: Operating System :: OS Independent
Requires-Dist: websocket-client
Requires-Dist: urllib3
Requires-Dist: privex-helpers
Requires-Dist: ecdsa (>=0.13)
